dupla/__init__.py
dupla/_version.txt
dupla/abstract_payload.py
dupla/api_keys.py
dupla/base.py
dupla/custom_types.py
dupla/endpoint.py
dupla/exceptions.py
dupla/payload.py
dupla/timestamp.py
dupla/validation.py
dupla/version.py
dupla-0.2.0.dist-info/licenses/LICENSE
dupla-0.2.0.dist-info/METADATA
dupla-0.2.0.dist-info/WHEEL
dupla-0.2.0.dist-info/top_level.txt
dupla-0.2.0.dist-info/RECORD
