Metadata-Version: 2.4
Name: dupla
Version: 0.2.0
Summary: A python API for making requests to DUPLA (Dataudvekslingsplatformen)
Author-email: Valentin Rosenberg Larsen <valentin.rosenberg@gmail.com>, Alexander Tygesen <atygesen@hotmail.com>
License: Apache License 2.0
Classifier: Programming Language :: Python :: 3
Classifier: License :: OSI Approved :: Apache Software License
Classifier: Operating System :: OS Independent
Requires-Python: >=3.9
License-File: LICENSE
Requires-Dist: requests
Requires-Dist: requests_pkcs12
Requires-Dist: python-dotenv
Requires-Dist: pyyaml
Requires-Dist: backoff
Requires-Dist: packaging
Requires-Dist: pydantic>=2.1
Provides-Extra: test
Requires-Dist: pytest; extra == "test"
Requires-Dist: pytest-mock; extra == "test"
Requires-Dist: Faker; extra == "test"
Provides-Extra: dev
Requires-Dist: pytest; extra == "dev"
Requires-Dist: pytest-mock; extra == "dev"
Requires-Dist: Faker; extra == "dev"
Requires-Dist: black==23.7.0; extra == "dev"
Requires-Dist: ruff==0.1.5; extra == "dev"
Requires-Dist: pre-commit; extra == "dev"
Requires-Dist: build; extra == "dev"
Requires-Dist: twine; extra == "dev"
Requires-Dist: pyclean>=2.0.0; extra == "dev"
Dynamic: license-file
